Metadata-Version: 1.1
Name: tap-strava
Version: 0.0.1
Summary: Singer.io tap for extracting data from the Strava API
Home-page: UNKNOWN
Author: bsloane@gmail.com
Author-email: UNKNOWN
License: UNKNOWN
Platform: UNKNOWN
Classifier: Programming Language :: Python :: 3 :: Only
